pyconcord-0.4.6.dist-info/RECORD
pyconcord-0.4.6.dist-info/METADATA
pyconcord-0.4.6.dist-info/WHEEL
pyconcord-0.4.6.dist-info/licenses/LICENSE
pyconcord/_core.cpython-312-x86_64-linux-gnu.so
pyconcord/__init__.py
pyconcord/robsel.py
